kothonic/__init__.py
kothonic/py.typed
kothonic/utils.py
kothonic/builtins_ext/__init__.py
kothonic/builtins_ext/float_ext.py
kothonic/builtins_ext/int_ext.py
kothonic/builtins_ext/kotlin_extend.py
kothonic/builtins_ext/list_ext.py
kothonic/builtins_ext/map_ext.py
kothonic/builtins_ext/set_ext.py
kothonic/builtins_ext/str_ext.py
kothonic/collections/__init__.py
kothonic/collections/functions/empty_list.py
kothonic/collections/functions/empty_map.py
kothonic/collections/functions/empty_set.py
kothonic/collections/functions/list_of.py
kothonic/collections/functions/map_of.py
kothonic/collections/functions/set_of.py
kothonic/collections/types/collection.py
kothonic/collections/types/indexed_value.py
kothonic/collections/types/iterable.py
kothonic/collections/types/iterator.py
kothonic/collections/types/list.py
kothonic/collections/types/map.py
kothonic/collections/types/set.py
kothonic/core_features/__init__.py
kothonic/core_features/inline_value.py
kothonic/core_features/it_accessor.py
kothonic/core_features/kotlin_value.py
kothonic/core_features/variables.py
kothonic/core_features/functions/extension.py
kothonic/core_features/functions/println.py
kothonic/core_features/functions/readln.py
kothonic/core_features/types/abstract_class.py
kothonic/core_features/types/generics.py
kothonic/core_features/types/interface.py
kothonic/core_features/types/null.py
kothonic/core_features/types/nullable.py
kothonic/core_features/types/object.py
kothonic/core_features/types/data_class/dataclass.py
kothonic/core_features/types/data_class/dataclass_meta.py
kothonic/core_features/types/sealed_class/sealed.py
kothonic/core_features/types/sealed_class/sealed_meta.py
kothonic/random/__init__.py
kothonic/random/random.py
kothonic/stdlib/__init__.py
kothonic/stdlib/exceptions/illegal_state_exception.py
kothonic/stdlib/functions/apply.py
kothonic/stdlib/functions/assert_.py
kothonic/stdlib/functions/check.py
kothonic/stdlib/functions/check_not_null.py
kothonic-0.1.0.dist-info/licenses/LICENSE
kothonic-0.1.0.dist-info/METADATA
kothonic-0.1.0.dist-info/WHEEL
kothonic-0.1.0.dist-info/top_level.txt
kothonic-0.1.0.dist-info/RECORD
