Metadata-Version: 2.4
Name: kothonic
Version: 0.1.0
Summary: Bridging Python and Kotlin type systems for improved interoperability and readability.
Author: Matt
License: MIT License
Keywords: kotlin,interoperability,standard-library,monkey-patching
Classifier: Development Status :: 2 - Pre-Alpha
Classifier: Intended Audience :: Developers
Classifier: License :: OSI Approved :: MIT License
Classifier: Topic :: Software Development :: Libraries :: Python Modules
Requires-Python: >=3.10
License-File: LICENSE
Requires-Dist: typing-extensions>=4.0.0
Requires-Dist: forbiddenfruit>=0.1.4
Dynamic: license-file
